aiodynamo/__init__.py
aiodynamo/client.py
aiodynamo/credentials.py
aiodynamo/errors.py
aiodynamo/expressions.py
aiodynamo/http/__init__.py
aiodynamo/http/aiohttp.py
aiodynamo/http/httpx.py
aiodynamo/http/types.py
aiodynamo/models.py
aiodynamo/operations.py
aiodynamo/py.typed
aiodynamo/sign.py
aiodynamo/types.py
aiodynamo/utils.py
aiodynamo-24.1.dist-info/LICENSE
aiodynamo-24.1.dist-info/METADATA
aiodynamo-24.1.dist-info/WHEEL
aiodynamo-24.1.dist-info/RECORD
