Metadata-Version: 2.1
Name: aiodynamo
Version: 24.1
Summary: Asyncio DynamoDB client
Home-page: https://github.com/HENNGE/aiodynamo
License: Apache-2.0
Keywords: dynamodb,asyncio,aws
Author: Jonas Obrist
Author-email: jonas.obrist@hennge.com
Requires-Python: >=3.8,<4.0
Classifier: Framework :: AsyncIO
Classifier: License :: OSI Approved :: Apache Software License
Classifier: Programming Language :: Python :: 3
Classifier: Programming Language :: Python :: 3.8
Classifier: Programming Language :: Python :: 3.9
Classifier: Programming Language :: Python :: 3.10
Classifier: Programming Language :: Python :: 3.11
Classifier: Programming Language :: Python :: 3.12
Classifier: Programming Language :: Python :: 3 :: Only
Classifier: Typing :: Typed
Provides-Extra: aiohttp
Provides-Extra: httpx
Requires-Dist: aiohttp (>=3.6.2,<4.0.0) ; extra == "aiohttp"
Requires-Dist: httpx (>=0.15.0,<1.0.0) ; extra == "httpx"
Requires-Dist: yarl (>=1.4.2,<2.0.0)
Project-URL: Documentation, https://aiodynamo.readthedocs.io
Project-URL: Repository, https://github.com/HENNGE/aiodynamo
